parquet_tools/__init__.py
parquet_tools/cli.py
parquet_tools/commands/__init__.py
parquet_tools/commands/csv.py
parquet_tools/commands/inspect.py
parquet_tools/commands/show.py
parquet_tools/commands/utils.py
parquet_tools/gen_py/__init__.py
parquet_tools/gen_py/parquet/__init__.py
parquet_tools/gen_py/parquet/constants.py
parquet_tools/gen_py/parquet/ttypes.py
parquet_tools/parquet/__init__.py
parquet_tools/parquet/reader.py
parquet_tools-0.2.15.dist-info/LICENSE.txt
parquet_tools-0.2.15.dist-info/METADATA
parquet_tools-0.2.15.dist-info/WHEEL
parquet_tools-0.2.15.dist-info/entry_points.txt
parquet_tools-0.2.15.dist-info/RECORD
