Metadata-Version: 2.1
Name: parquet-tools
Version: 0.2.15
Summary: Easy install parquet-tools
Home-page: https://github.com/ktrueda/parquet-tools
License: MIT
Keywords: parquet-tools,parquet
Author: Kentaro Ueda
Author-email: kentaro.ueda.kentaro@gmail.com
Requires-Python: >=3.8
Classifier: License :: OSI Approved :: MIT License
Classifier: Programming Language :: Python :: 3
Classifier: Programming Language :: Python :: 3.8
Classifier: Programming Language :: Python :: 3.9
Classifier: Programming Language :: Python :: 3.10
Classifier: Programming Language :: Python :: 3.11
Requires-Dist: boto3 (>=1.34.11,<2.0.0)
Requires-Dist: colorama (>=0.4.6,<0.5.0)
Requires-Dist: halo (>=0.0.31,<0.0.32)
Requires-Dist: pandas (>=2.1.4,<3.0.0)
Requires-Dist: pyarrow
Requires-Dist: tabulate (>=0.9.0,<0.10.0)
Requires-Dist: thrift (>=0.16.0,<0.17.0)
Project-URL: Repository, https://github.com/ktrueda/parquet-tools
